paykassa/__init__.py
paykassa/dto.py
paykassa/merchant.py
paykassa/payment.py
paykassa/struct.py
paykassa_api_sdk-1.2.0.dist-info/licenses/LICENSE
paykassa_api_sdk-1.2.0.dist-info/METADATA
paykassa_api_sdk-1.2.0.dist-info/WHEEL
paykassa_api_sdk-1.2.0.dist-info/top_level.txt
paykassa_api_sdk-1.2.0.dist-info/RECORD
