Metadata-Version: 2.4
Name: paykassa-api-sdk
Version: 1.2.0
Summary: Paykassa API & SCI
Home-page: https://paykassa.pro
Author: Vadim Selyakov
Author-email: selyakovadim@gmail.com
Project-URL: Source, https://github.com/paykassa-dev/python-api-sdk
Project-URL: Documentation, https://paykassa.pro/en/developers/
Classifier: Intended Audience :: Developers
Classifier: Programming Language :: Python
Classifier: Programming Language :: Python :: 3.6
Classifier: Programming Language :: Python :: 3.7
Classifier: Programming Language :: Python :: 3.8
Classifier: Programming Language :: Python :: 3.9
Classifier: Programming Language :: Python :: 3.10
Classifier: License :: OSI Approved :: MIT License
Classifier: Operating System :: OS Independent
Requires-Python: >=3.6
License-File: LICENSE
Requires-Dist: requests<3,>=2.7
Dynamic: license-file
